pdoc3_files/__init__.py
pdoc3_files/document.py
pdoc3_files-0.1.0.dist-info/LICENSE
pdoc3_files-0.1.0.dist-info/METADATA
pdoc3_files-0.1.0.dist-info/WHEEL
pdoc3_files-0.1.0.dist-info/entry_points.txt
pdoc3_files-0.1.0.dist-info/top_level.txt
pdoc3_files-0.1.0.dist-info/RECORD
