Metadata-Version: 2.1
Name: pdoc3-files
Version: 0.1.0
Summary: Bulk Python file documentation generator using pdoc3.
Home-page: https://github.com/firgaty/pdoc3-files
Author: Félix Desmaretz
Author-email: felix.desmaretz@protonmail.com
License: UNKNOWN
Platform: UNKNOWN
Classifier: Programming Language :: Python :: 3
Classifier: License :: OSI Approved :: GNU General Public License v3 (GPLv3)
Classifier: Operating System :: OS Independent
Requires-Python: >=3.6
License-File: LICENSE
